Metadata-Version: 2.1
Name: oneNeuron-pypi-shardul0701
Version: 0.0.2
Summary: it's a implementation of Perceptron
Home-page: https://github.com/shardul0701/oneNeuron_pypi
Author: shardul0701
Author-email: shardulmehetar07@gmail.com
License: UNKNOWN
Project-URL: Bug Tracker, https://github.com/shardul0701/oneNeuron_pypi/issues
Platform: UNKNOWN
Classifier: Programming Language :: Python :: 3
Classifier: License :: OSI Approved :: MIT License
Classifier: Operating System :: OS Independent
Requires-Python: >=3.6
License-File: LICENSE
Requires-Dist: numpytqdmloggingpandasjoblibmatplotlib
